<annotation>
  <folder>VOC2007</folder>
  <filename>Decomp46.jpg</filename>
  <segmented>0</segmented>
  <size>
    <width>2000</width>
    <height>500</height>
    <depth>1</depth>
  </size>
  <object>
    <name>Decomposed</name>
    <pose>Unspecified</pose>
    <truncated>0</truncated>
    <difficult>0</difficult>
    <bndbox>
      <xmin>183</xmin>
      <ymin>247</ymin>
      <xmax>214</xmax>
      <ymax>275</ymax>
    </bndbox>
  </object>
  <object>
    <name>Decomposed</name>
    <pose>Unspecified</pose>
    <truncated>0</truncated>
    <difficult>0</difficult>
    <bndbox>
      <xmin>1255</xmin>
      <ymin>153</ymin>
      <xmax>1271</xmax>
      <ymax>170</ymax>
    </bndbox>
  </object>
  <object>
    <name>Decomposed</name>
    <pose>Unspecified</pose>
    <truncated>0</truncated>
    <difficult>0</difficult>
    <bndbox>
      <xmin>1189</xmin>
      <ymin>194</ymin>
      <xmax>1205</xmax>
      <ymax>213</ymax>
    </bndbox>
  </object>
  <object>
    <name>Decomposed</name>
    <pose>Unspecified</pose>
    <truncated>0</truncated>
    <difficult>0</difficult>
    <bndbox>
      <xmin>1582</xmin>
      <ymin>249</ymin>
      <xmax>1599</xmax>
      <ymax>269</ymax>
    </bndbox>
  </object>
</annotation>
